{
    "input-60": [
        {
            "bottom": 354,
            "left": 534,
            "top": 341,
            "right": 547
        }
    ],
    "input-38": [
        {
            "bottom": 711,
            "left": 534,
            "top": 698,
            "right": 547
        }
    ],
    "input-54": [
        {
            "bottom": 471,
            "left": 182,
            "top": 458,
            "right": 195
        }
    ],
    "input-56": [
        {
            "bottom": 471,
            "left": 52,
            "top": 458,
            "right": 65
        }
    ],
    "input-31": [
        {
            "bottom": 335,
            "left": 324,
            "top": 273,
            "right": 606
        }
    ],
    "input-58": [
        {
            "bottom": 371,
            "left": 573,
            "top": 358,
            "right": 586
        }
    ],
    "input-53": [
        {
            "bottom": 506,
            "left": 31,
            "top": 493,
            "right": 44
        }
    ],
    "input-28": [
        {
            "bottom": 678,
            "left": 324,
            "top": 612,
            "right": 606
        }
    ],
    "input-34": [
        {
            "bottom": 413,
            "left": 30,
            "top": 390,
            "right": 311
        }
    ],
    "input-69": [
        {
            "bottom": 218,
            "left": 80,
            "top": 218,
            "right": 126
        }
    ],
    "input-29": [
        {
            "bottom": 599,
            "left": 324,
            "top": 529,
            "right": 606
        }
    ],
    "input-66": [
        {
            "bottom": 257,
            "left": 573,
            "top": 244,
            "right": 586
        }
    ],
    "input-43": [
        {
            "bottom": 600,
            "left": 52,
            "top": 588,
            "right": 64
        }
    ],
    "input-49": [
        {
            "bottom": 536,
            "left": 52,
            "top": 524,
            "right": 64
        }
    ],
    "input-24": [
        {
            "bottom": 870,
            "left": 324,
            "top": 804,
            "right": 605
        }
    ],
    "input-63": [
        {
            "bottom": 306,
            "left": 82,
            "top": 294,
            "right": 95
        }
    ],
    "input-26": [
        {
            "bottom": 791,
            "left": 324,
            "top": 727,
            "right": 606
        }
    ],
    "input-45": [
        {
            "bottom": 585,
            "left": 30,
            "top": 573,
            "right": 43
        }
    ],
    "input-48": [
        {
            "bottom": 552,
            "left": 52,
            "top": 539,
            "right": 65
        }
    ],
    "input-46": [
        {
            "bottom": 568,
            "left": 31,
            "top": 556,
            "right": 44
        }
    ],
    "input-27": [
        {
            "bottom": 737,
            "left": 29,
            "top": 690,
            "right": 311
        }
    ],
    "input-59": [
        {
            "bottom": 371,
            "left": 534,
            "top": 359,
            "right": 547
        }
    ],
    "input-44": [
        {
            "bottom": 600,
            "left": 144,
            "top": 588,
            "right": 157
        }
    ],
    "input-33": [
        {
            "bottom": 372,
            "left": 30,
            "top": 324,
            "right": 311
        }
    ],
    "input-39": [
        {
            "bottom": 676,
            "left": 238,
            "top": 662,
            "right": 251
        }
    ],
    "input-41": [
        {
            "bottom": 621,
            "left": 31,
            "top": 608,
            "right": 44
        }
    ],
    "input-37": [
        {
            "bottom": 711,
            "left": 573,
            "top": 699,
            "right": 586
        }
    ],
    "input-36": [
        {
            "bottom": 755,
            "left": 277,
            "top": 743,
            "right": 290
        }
    ],
    "input-25": [
        {
            "bottom": 808,
            "left": 29,
            "top": 770,
            "right": 311
        }
    ],
    "input-42": [
        {
            "bottom": 600,
            "left": 219,
            "top": 588,
            "right": 232
        }
    ],
    "input-35": [
        {
            "bottom": 756,
            "left": 238,
            "top": 744,
            "right": 251
        }
    ],
    "input-65": [
        {
            "bottom": 258,
            "left": 534,
            "top": 245,
            "right": 547
        }
    ],
    "input-23": [
        {
            "bottom": 870,
            "left": 28,
            "top": 821,
            "right": 310
        }
    ],
    "input-40": [
        {
            "bottom": 675,
            "left": 278,
            "top": 663,
            "right": 291
        }
    ],
    "input-61": [
        {
            "bottom": 353,
            "left": 573,
            "top": 341,
            "right": 586
        }
    ],
    "input-47": [
        {
            "bottom": 536,
            "left": 180,
            "top": 524,
            "right": 193
        }
    ],
    "input-30": [
        {
            "bottom": 463,
            "left": 323,
            "top": 389,
            "right": 605
        }
    ],
    "input-64": [
        {
            "bottom": 306,
            "left": 30,
            "top": 294,
            "right": 43
        }
    ],
    "input-52": [
        {
            "bottom": 511,
            "left": 534,
            "top": 499,
            "right": 547
        }
    ],
    "input-68": [
        {
            "bottom": 251,
            "left": 203,
            "top": 251,
            "right": 253
        }
    ],
    "input-55": [
        {
            "bottom": 488,
            "left": 52,
            "top": 475,
            "right": 65
        }
    ],
    "input-67": [
        {
            "bottom": 195,
            "left": 73,
            "top": 195,
            "right": 116
        }
    ],
    "input-50": [
        {
            "bottom": 521,
            "left": 52,
            "top": 509,
            "right": 65
        }
    ],
    "input-57": [
        {
            "bottom": 456,
            "left": 31,
            "top": 443,
            "right": 44
        }
    ],
    "input-62": [
        {
            "bottom": 306,
            "left": 140,
            "top": 294,
            "right": 153
        }
    ],
    "input-32": [
        {
            "bottom": 288,
            "left": 30,
            "top": 263,
            "right": 141
        }
    ],
    "input-51": [
        {
            "bottom": 512,
            "left": 573,
            "top": 499,
            "right": 586
        }
    ]
}