{
    "input-55": [
        {
            "bottom": 330,
            "left": 84,
            "right": 283,
            "top": 315
        },
        {
            "bottom": 346,
            "left": 84,
            "right": 283,
            "top": 330
        }
    ],
    "input-43": [
        {
            "bottom": 626,
            "left": 116,
            "right": 283,
            "top": 611
        }
    ],
    "input-66": [
        {
            "bottom": 270,
            "left": 193,
            "right": 302,
            "top": 270
        }
    ],
    "input-51": [
        {
            "bottom": 70,
            "left": 44,
            "right": 283,
            "top": 55
        },
        {
            "bottom": 86,
            "left": 44,
            "right": 283,
            "top": 70
        },
        {
            "bottom": 102,
            "left": 44,
            "right": 283,
            "top": 86
        }
    ],
    "input-57": [
        {
            "bottom": 460,
            "left": 368,
            "right": 567,
            "top": 445
        }
    ],
    "input-50": [
        {
            "bottom": 54,
            "left": 344,
            "right": 567,
            "top": 39
        }
    ],
    "input-59": [
        {
            "bottom": 644,
            "left": 368,
            "right": 567,
            "top": 629
        }
    ],
    "input-48": [
        {
            "bottom": 94,
            "left": 400,
            "right": 567,
            "top": 79
        }
    ],
    "input-61": [
        {
            "bottom": 708,
            "left": 368,
            "right": 567,
            "top": 693
        },
        {
            "bottom": 724,
            "left": 368,
            "right": 567,
            "top": 708
        },
        {
            "bottom": 740,
            "left": 368,
            "right": 567,
            "top": 724
        }
    ],
    "input-58": [
        {
            "bottom": 586,
            "left": 60,
            "right": 283,
            "top": 571
        }
    ],
    "input-54": [
        {
            "bottom": 298,
            "left": 368,
            "right": 567,
            "top": 283
        },
        {
            "bottom": 314,
            "left": 368,
            "right": 567,
            "top": 298
        },
        {
            "bottom": 330,
            "left": 368,
            "right": 567,
            "top": 315
        },
        {
            "bottom": 346,
            "left": 368,
            "right": 567,
            "top": 330
        },
        {
            "bottom": 362,
            "left": 368,
            "right": 567,
            "top": 346
        },
        {
            "bottom": 378,
            "left": 368,
            "right": 567,
            "top": 363
        }
    ],
    "input-53": [
        {
            "bottom": 266,
            "left": 84,
            "right": 283,
            "top": 251
        }
    ],
    "input-44": [
        {
            "bottom": 122,
            "left": 400,
            "right": 487,
            "top": 107
        }
    ],
    "input-62": [
        {
            "bottom": 472,
            "left": 60,
            "right": 71,
            "top": 461
        }
    ],
    "input-49": [
        {
            "bottom": 428,
            "left": 480,
            "right": 567,
            "top": 413
        }
    ],
    "input-64": [
        {
            "bottom": 268,
            "left": 344,
            "right": 355,
            "top": 257
        }
    ],
    "input-63": [
        {
            "bottom": 400,
            "left": 344,
            "right": 355,
            "top": 389
        }
    ],
    "input-65": [
        {
            "bottom": 233,
            "left": 60,
            "right": 71,
            "top": 222
        }
    ],
    "input-40": [
        {
            "bottom": 674,
            "left": 116,
            "right": 283,
            "top": 659
        }
    ],
    "input-47": [
        {
            "bottom": 74,
            "left": 400,
            "right": 567,
            "top": 59
        }
    ],
    "input-52": [
        {
            "bottom": 158,
            "left": 44,
            "right": 283,
            "top": 143
        },
        {
            "bottom": 174,
            "left": 44,
            "right": 283,
            "top": 158
        },
        {
            "bottom": 190,
            "left": 44,
            "right": 283,
            "top": 174
        }
    ],
    "input-42": [
        {
            "bottom": 606,
            "left": 116,
            "right": 283,
            "top": 591
        }
    ],
    "input-41": [
        {
            "bottom": 702,
            "left": 116,
            "right": 283,
            "top": 687
        }
    ],
    "input-46": [
        {
            "bottom": 170,
            "left": 400,
            "right": 567,
            "top": 155
        }
    ],
    "input-45": [
        {
            "bottom": 142,
            "left": 400,
            "right": 567,
            "top": 127
        }
    ],
    "input-39": [
        {
            "bottom": 654,
            "left": 116,
            "right": 203,
            "top": 639
        }
    ],
    "input-60": [
        {
            "bottom": 676,
            "left": 368,
            "right": 567,
            "top": 661
        }
    ],
    "input-56": [
        {
            "bottom": 434,
            "left": 84,
            "right": 283,
            "top": 419
        },
        {
            "bottom": 450,
            "left": 84,
            "right": 283,
            "top": 434
        }
    ]
}